README
setup.py
bookreader/__init__.py
bookreader/admin.py
bookreader/context_processors.py
bookreader/export.py
bookreader/fields.py
bookreader/forms.py
bookreader/models.py
bookreader/settings.py
bookreader/urls.py
bookreader.egg-info/PKG-INFO
bookreader.egg-info/SOURCES.txt
bookreader.egg-info/dependency_links.txt
bookreader.egg-info/not-zip-safe
bookreader.egg-info/requires.txt
bookreader.egg-info/top_level.txt
bookreader/fixtures/tests/collection.json
bookreader/fixtures/tests/repository.json
bookreader/fixtures/tests/harvesting/book.xml
bookreader/harvesting/__init__.py
bookreader/harvesting/book.py
bookreader/harvesting/collection.py
bookreader/harvesting/metadata.py
bookreader/migrations/0001_v0_7.py
bookreader/migrations/0002_v0_8.py
bookreader/migrations/0003_v0_9_add_fields.py
bookreader/migrations/0004_v0_9_data_migration.py
bookreader/migrations/0005_v0_9_remove_flag.py
bookreader/migrations/__init__.py
bookreader/signals/__init__.py
bookreader/signals/book.py
bookreader/signals/collection.py
bookreader/signals/repository.py
bookreader/templatetags/__init__.py
bookreader/templatetags/bookreader_compare.py
bookreader/templatetags/bookreader_djatoka.py
bookreader/tests/__init__.py
bookreader/tests/fakes.py
bookreader/tests/fields.py
bookreader/tests/oai.py
bookreader/tests/bitstream/canonical/bitstream_metadata.xml
bookreader/tests/bitstream/extant/bitstream_metadata.xml
bookreader/tests/bitstream/frankenbook/bitstream_metadata.xml
bookreader/tests/bitstream/work/bitstream_metadata.xml
bookreader/tests/harvesting/__init__.py
bookreader/tests/harvesting/book.py
bookreader/tests/harvesting/collection.py
bookreader/tests/oai/0003_dim.xml
bookreader/tests/oai/0003_ore.xml
bookreader/tests/oai/91216_dim.xml
bookreader/tests/oai/91216_ore.xml
bookreader/tests/oai/91217_dim.xml
bookreader/tests/oai/91217_ore.xml
bookreader/tests/oai/collection_identifiers.xml
bookreader/tests/oai/collections.xml
bookreader/tests/oai/identify.xml
bookreader/tests/oai/mapping.txt
bookreader/views/__init__.py
bookreader/views/book.py
bookreader/views/collection.py
bookreader/views/editor.py
bookreader/views/harvesting.py
bookreader/views/page.py
bookreader/views/pdf.py
