Metadata-Version: 1.0
Name: bookreader
Version: 1.0
Summary: A Django book reading application that utilizes Djatoka and a DSpace repository to present browseable views of scanned books.
Home-page: http://library.tamu.edu
Author: Texas A&M University Library
Author-email: webmaster@library.tamu.edu
License: UNKNOWN
Keywords: djatoka dspace
Platform: UNKNOWN
Classifier: Framework :: Django
Classifier: Programming Language :: Python
Classifier: Intended Audience :: Developers
Classifier: Intended Audience :: Education
Classifier: License :: OSI Approved :: Apache Software License
Classifier: Topic :: Software Development :: Libraries :: Python Modules
Classifier: Topic :: Education
Classifier: Development Status :: 4 - Beta
